{
  "username": "netflixnl",
  "profile_url": "https://www.tiktok.com/@netflixnl",
  "avatar_url": "https://p16-common-sign.tiktokcdn-us.com/tos-useast2a-avt-0068-euttp/ccc17f18fb15e174a9945cab85ec446f~tplv-tiktokx-cropcenter:1080:1080.jpeg?dr=9640&refresh_token=cb0339ed&x-expires=1778065200&x-signature=OnYRpdteWTCor%2BBQb6BnhB0H%2BHY%3D&t=4d5b0474&ps=13740610&shp=a5d48078&shcp=81f88b70&idc=useast8",
  "content_type": "image/jpeg",
  "sha256": "42895851c1365a307c27817a95d48e09cb740c0c7dd675c1ab4770fda683623b",
  "image_file": "avatar.jpg",
  "downloaded_at_unix": 1777894947
}