{
  "username": "lucaspelizaro",
  "profile_url": "https://www.tiktok.com/@lucaspelizaro",
  "avatar_url": "https://p16-common-sign.tiktokcdn-us.com/tos-useast2a-avt-0068-euttp/13ced284ebc3c65576107fb878fce54a~tplv-tiktokx-cropcenter:1080:1080.jpeg?dr=9640&refresh_token=8cf13bd1&x-expires=1778065200&x-signature=hVFzPUKtd%2FinOU3856T5rUFnYNc%3D&t=4d5b0474&ps=13740610&shp=a5d48078&shcp=81f88b70&idc=useast8",
  "content_type": "image/jpeg",
  "sha256": "758d0edb05b28d86cd181015a18d67db7bd312d809b499491c1046b5af1448a5",
  "image_file": "avatar.jpg",
  "downloaded_at_unix": 1777894930
}